sphinx_c_autodoc/__init__.py
sphinx_c_autodoc/loader.py
sphinx_c_autodoc/apidoc/__init__.py
sphinx_c_autodoc/apidoc/templates/header.rst.jinja2
sphinx_c_autodoc/apidoc/templates/source.rst.jinja2
sphinx_c_autodoc/apidoc/templates/toc.rst.jinja2
sphinx_c_autodoc/clang/__init__.py
sphinx_c_autodoc/clang/comments.py
sphinx_c_autodoc/clang/patches.py
sphinx_c_autodoc/domains/__init__.py
sphinx_c_autodoc/domains/c.py
sphinx_c_autodoc/napoleon/__init__.py
sphinx_c_autodoc/viewcode/__init__.py
sphinx_c_autodoc-1.6.0.dist-info/entry_points.txt
sphinx_c_autodoc-1.6.0.dist-info/licenses/LICENSE-MIT
sphinx_c_autodoc-1.6.0.dist-info/WHEEL
sphinx_c_autodoc-1.6.0.dist-info/METADATA
sphinx_c_autodoc-1.6.0.dist-info/RECORD
