Metadata-Version: 2.4
Name: sphinx-c-autodoc
Version: 1.6.0
Summary: A sphinx autodoc extension for c modules
Author: Nick
Requires-Python: >=3.10
Classifier: Development Status :: 5 - Production/Stable
Classifier: Framework :: Sphinx :: Extension
Classifier: Operating System :: OS Independent
Classifier: License :: OSI Approved :: The Unlicense (Unlicense)
Classifier: License :: OSI Approved :: MIT License
License-File: LICENSE-MIT
Requires-Dist: sphinx>=4.0
Requires-Dist: clang>=12
Requires-Dist: beautifulsoup4
Project-URL: documentation, https://sphinx-c-autodoc.readthedocs.io/en/latest/
Project-URL: repository, https://github.com/speedyleion/sphinx-c-autodoc
